pyDismail/__init__.py
pyDismail/dismail.py
pyDismail-2.3.dist-info/LICENSE
pyDismail-2.3.dist-info/METADATA
pyDismail-2.3.dist-info/WHEEL
pyDismail-2.3.dist-info/top_level.txt
pyDismail-2.3.dist-info/RECORD
