Metadata-Version: 2.1
Name: pyDismail
Version: 2.3
Summary: an API wrapper for yadim.dismail.de, a disposable mail provider
Home-page: https://github.com/scrubjay55/pyDismail.git
Author: scrubjay55
License: APLv2
Project-URL: Source, https://github.com/scrubjay55/pyDismail.git
Platform: UNKNOWN
License-File: LICENSE
Requires-Dist: requests
Requires-Dist: eml-parser
